libcfinder/__init__.py
libcfinder/libcfinder.py
libcfinder/db/libc6-amd64_2.10.1-0ubuntu15_i386.symbols
libcfinder/db/libc6-amd64_2.10.1-0ubuntu19_i386.symbols
libcfinder/db/libc6-amd64_2.11.1-0ubuntu7.11_i386.symbols
libcfinder/db/libc6-amd64_2.11.1-0ubuntu7.12_i386.symbols
libcfinder/db/libc6-amd64_2.11.1-0ubuntu7.21_i386.symbols
libcfinder/db/libc6-amd64_2.11.1-0ubuntu7_i386.symbols
libcfinder/db/libc6-amd64_2.12.1-0ubuntu10.4_i386.symbols
libcfinder/db/libc6-amd64_2.12.1-0ubuntu6_i386.symbols
libcfinder/db/libc6-amd64_2.13-0ubuntu13.2_i386.symbols
libcfinder/db/libc6-amd64_2.13-0ubuntu13_i386.symbols
libcfinder/db/libc6-amd64_2.13-20ubuntu5.2_i386.symbols
libcfinder/db/libc6-amd64_2.13-20ubuntu5.3_i386.symbols
libcfinder/db/libc6-amd64_2.13-20ubuntu5_i386.symbols
libcfinder/db/libc6-amd64_2.15-0ubuntu10.18_i386.symbols
libcfinder/db/libc6-amd64_2.15-0ubuntu10_i386.symbols
libcfinder/db/libc6-amd64_2.15-0ubuntu20.2_i386.symbols
libcfinder/db/libc6-amd64_2.15-0ubuntu20_i386.symbols
libcfinder/db/libc6-amd64_2.17-0ubuntu5.1_i386.symbols
libcfinder/db/libc6-amd64_2.17-0ubuntu5_i386.symbols
libcfinder/db/libc6-amd64_2.17-93ubuntu4_i386.symbols
libcfinder/db/libc6-amd64_2.19-0ubuntu6.14_i386.symbols
libcfinder/db/libc6-amd64_2.19-0ubuntu6.15_i386.symbols
libcfinder/db/libc6-amd64_2.19-0ubuntu6_i386.symbols
libcfinder/db/libc6-amd64_2.19-10ubuntu2.3_i386.symbols
libcfinder/db/libc6-amd64_2.19-10ubuntu2_i386.symbols
libcfinder/db/libc6-amd64_2.21-0ubuntu4.3_i386.symbols
libcfinder/db/libc6-amd64_2.21-0ubuntu4_i386.symbols
libcfinder/db/libc6-amd64_2.23-0ubuntu10_i386.symbols
libcfinder/db/libc6-amd64_2.23-0ubuntu11_i386.symbols
libcfinder/db/libc6-amd64_2.23-0ubuntu3_i386.symbols
libcfinder/db/libc6-amd64_2.24-3ubuntu1_i386.symbols
libcfinder/db/libc6-amd64_2.24-3ubuntu2.2_i386.symbols
libcfinder/db/libc6-amd64_2.24-9ubuntu2.2_i386.symbols
libcfinder/db/libc6-amd64_2.24-9ubuntu2_i386.symbols
libcfinder/db/libc6-amd64_2.26-0ubuntu2.1_i386.symbols
libcfinder-1.0.6.dist-info/METADATA
libcfinder-1.0.6.dist-info/WHEEL
libcfinder-1.0.6.dist-info/top_level.txt
libcfinder-1.0.6.dist-info/RECORD
