Metadata-Version: 2.1
Name: libcfinder
Version: 1.0.6
Summary: UNKNOWN
Home-page: https://github.com/petitnau/libcfinder
Author: Roberto Pettinau
Author-email: roberto.pettinau99@gmail.com
License: UNKNOWN
Platform: UNKNOWN
Classifier: Programming Language :: Python :: 3
Classifier: Topic :: Security
Requires-Dist: beautifulsoup4
Requires-Dist: requests
